pygame_intro/__init__.py
pygame_intro/__main__.py
pygame_intro/example.py
pygame_intro/intro.py
pygame_intro/test.py
pygame_intro-1.3.1.dist-info/licenses/LICENSE.txt
pygame_intro-1.3.1.dist-info/METADATA
pygame_intro-1.3.1.dist-info/WHEEL
pygame_intro-1.3.1.dist-info/top_level.txt
pygame_intro-1.3.1.dist-info/RECORD
