Metadata-Version: 2.4
Name: pygame_intro
Version: 1.3.1
Summary: A intro module for pygame Community Edition.
Author-email: AntonisDevStuff <contact@antonisdevstuff.com>
License-Expression: MIT
Project-URL: Repository, https://github.com/antonisdevstuff/pygame-intro
Project-URL: Issues, https://github.com/antonisdevstuff/pygame-intro/issues
Project-URL: Releases, https://github.com/antonisdevstuff/pygame-intro/releases
Keywords: pygame,intro,splash screen
Classifier: Development Status :: 5 - Production/Stable
Classifier: Operating System :: Microsoft :: Windows
Classifier: Operating System :: POSIX :: Linux
Classifier: Operating System :: MacOS
Classifier: Programming Language :: Python :: 3
Classifier: Topic :: Software Development :: Libraries :: pygame
Requires-Python: >=3.11
License-File: LICENSE.txt
Requires-Dist: pygame-ce>=2.5.0
Dynamic: license-file
